MANIFEST.in
README.md
object_detection.ini
setup.py
autoOD.egg-info/PKG-INFO
autoOD.egg-info/SOURCES.txt
autoOD.egg-info/dependency_links.txt
autoOD.egg-info/requires.txt
autoOD.egg-info/top_level.txt
auto_od/__init__.py
auto_od/analyze/__init__.py
auto_od/analyze/auto_augment.py
auto_od/analyze/auto_model.py
auto_od/analyze/batch_select.py
auto_od/augm_test/__init__.py
auto_od/augm_test/augm.py
auto_od/augm_test/inside_augment.py
auto_od/core/__init__.py
auto_od/core/logger.py
auto_od/core/settings.py
auto_od/core/zoo_models.csv
auto_od/data_processing/__init__.py
auto_od/data_processing/annotations_processing/__init__.py
auto_od/data_processing/annotations_processing/base.py
auto_od/data_processing/annotations_processing/prepare_xml_data.py
auto_od/data_processing/dataset_processing/__init__.py
auto_od/data_processing/dataset_processing/all_data_dataset.py
auto_od/data_processing/dataset_processing/base.py
auto_od/data_processing/dataset_processing/train_test_datasets.py
auto_od/inference/__init__.py
auto_od/scenario_detection/__init__.py
auto_od/tflite/__init__.py
auto_od/tflite/tflite_generate.py
auto_od/training/__init__.py
auto_od/training/auto_training.py
auto_od/training/configuration/__init__.py
auto_od/training/configuration/augmentation.py
auto_od/training/configuration/config.py
auto_od/training/configuration/config_parser.py
auto_od/training/stop/__init__.py
auto_od/training/stop/early_stopping.py
auto_od/training/stop/stop_algo.py
auto_od/utils/__init__.py
auto_od/utils/decorators.py
auto_od/utils/info_messages.py