Metadata-Version: 2.1
Name: autoOD
Version: 1.0.2
Summary: Module to automate object detection process.
Author: Elina Chertova
Author-email: elas.2015@mail.ru
Keywords: ObjectDetection,autoML
